{"chunk_definitions":[{"row":28,"row_count":1,"visible":true,"expansion_state":0,"options":{"engine":"r","label":"unnamed-chunk-34","dev":"png"},"document_id":"95D18684","chunk_id":"cwilejqmh0r2t","chunk_label":"unnamed-chunk-1"},{"row":67,"row_count":1,"visible":true,"expansion_state":0,"options":{"engine":"r","label":"unnamed-chunk-105","dev":"png"},"document_id":"95D18684","chunk_id":"csqkz4d9e2zk9","chunk_label":"unnamed-chunk-2"},{"row":88,"row_count":1,"visible":true,"expansion_state":0,"options":{"engine":"r","label":"unnamed-chunk-106","dev":"png"},"document_id":"95D18684","chunk_id":"cwt4aydxzl11f","chunk_label":"unnamed-chunk-3"},{"row":110,"row_count":1,"visible":true,"expansion_state":0,"options":{"engine":"r","label":"unnamed-chunk-107","dev":"png"},"document_id":"95D18684","chunk_id":"cyzu7r2brexk3","chunk_label":"unnamed-chunk-4"},{"row":134,"row_count":1,"visible":true,"expansion_state":0,"options":{"engine":"r","label":"unnamed-chunk-63","dev":"png"},"document_id":"95D18684","chunk_id":"cge5pfxnn08sg","chunk_label":"unnamed-chunk-5"},{"row":166,"row_count":1,"visible":true,"expansion_state":0,"options":{"engine":"r","label":"unnamed-chunk-109","dev":"png"},"document_id":"95D18684","chunk_id":"caq0l8iilpl17","chunk_label":"unnamed-chunk-6"}],"doc_write_time":1716827722,"chunk_rendered_width":700}